ELEC 402/Assignment 1/fsm.sv

module train_FSM(
    input   clk, rst,
    //door_is_open = 1 when open, 0 when closed
    input   depart_ready,
            door_obstruction,
            door_is_open,
            near_station, 
            at_station,
            track_obstruction,
    input[7:0] cruise_speed, current_speed, crawl_speed,

    output logic    ctrl_door,
                    ctrl_brake,
                    ctrl_brake_emergency,
                    ctrl_motor_accelerate,
                    ctrl_motor_maintain
);

    logic [3:0] count;

    //states
    enum {
        s_idle,
        s_doors_opened,
        s_doors_closing,
        s_doors_closed,
        s_accelerate,
        s_maintain_speed,
        s_brake,
        s_emergency_brake,
        s_crawl,
        s_arrived,
        s_doors_opening,
        s_fault
    } state;


    //state transitions
    always_ff @(posedge clk) begin
        if(rst) state <= s_idle;
        else case(state)

            s_idle: state <= s_doors_opened;

            s_doors_opened: if(depart_ready) state <= s_doors_closing;

            s_doors_closing: begin
                if(door_obstruction) state <= s_doors_opening;
                else if(~door_is_open) state <= s_doors_closed;
            end

            s_doors_closed: state <= s_accelerate;

            s_accelerate: begin
                if(track_obstruction) state <= s_emergency_brake;
                else if(current_speed >= cruise_speed) state <= s_maintain_speed; 
            end

            s_maintain_speed: begin
                if(track_obstruction) state <= s_emergency_brake;
                else if(near_station) state <= s_brake;
            end

            s_brake: if(current_speed <= crawl_speed) state <= s_crawl;

            s_crawl: if(at_station) state <= s_arrived;

            s_arrived: if(current_speed == 0) state <= s_doors_opening;

            s_doors_opening: if(door_is_open) state <= s_doors_opened;

            s_emergency_brake: if(~track_obstruction) state <= s_accelerate;

            s_fault: state <= s_fault;
            default: state <= s_fault;
        endcase
    end

    //outputs (combinational)
    always_comb begin
        case(state)
            s_idle: begin
                ctrl_door               = 0;
                ctrl_brake              = 0;
                ctrl_brake_emergency    = 0;
                ctrl_motor_accelerate   = 0;
                ctrl_motor_maintain     = 0;
            end

            s_doors_opened: begin
                ctrl_door               = 1;
                ctrl_brake              = 1;
                ctrl_brake_emergency    = 0;
                ctrl_motor_accelerate   = 0;
                ctrl_motor_maintain     = 0;
            end

            s_doors_closing: begin
                ctrl_door               = 0;
                ctrl_brake              = 1;
                ctrl_brake_emergency    = 0;
                ctrl_motor_accelerate   = 0;
                ctrl_motor_maintain     = 0;
            end

            s_doors_closed: begin
                ctrl_door               = 0;
                ctrl_brake              = 1;
                ctrl_brake_emergency    = 0;
                ctrl_motor_accelerate   = 0;
                ctrl_motor_maintain     = 0;
            end

            s_accelerate: begin
                ctrl_door               = 0;
                ctrl_brake              = 0;
                ctrl_brake_emergency    = 0;
                ctrl_motor_accelerate   = 1;
                ctrl_motor_maintain     = 0;
            end

            s_maintain_speed: begin
                ctrl_door               = 0;
                ctrl_brake              = 0;
                ctrl_brake_emergency    = 0;
                ctrl_motor_accelerate   = 0;
                ctrl_motor_maintain     = 1;
            end

            s_brake: begin
                ctrl_door               = 0;
                ctrl_brake              = 1;
                ctrl_brake_emergency    = 0;
                ctrl_motor_accelerate   = 0;
                ctrl_motor_maintain     = 0;
            end

            s_crawl: begin
                ctrl_door               = 0;
                ctrl_brake              = 0;
                ctrl_brake_emergency    = 0;
                ctrl_motor_accelerate   = 0;
                ctrl_motor_maintain     = 1;
            end

            s_arrived: begin
                ctrl_door               = 0;
                ctrl_brake              = 1;
                ctrl_brake_emergency    = 0;
                ctrl_motor_accelerate   = 0;
                ctrl_motor_maintain     = 0;
            end

            s_doors_opening: begin
                ctrl_door               = 1;
                ctrl_brake              = 1;
                ctrl_brake_emergency    = 0;
                ctrl_motor_accelerate   = 0;
                ctrl_motor_maintain     = 0;
            end

            s_emergency_brake: begin
                ctrl_door               = 0;
                ctrl_brake              = 0;
                ctrl_brake_emergency    = 1;
                ctrl_motor_accelerate   = 0;
                ctrl_motor_maintain     = 0;
            end

            s_fault: begin
                ctrl_door               = 1'bz;
                ctrl_brake              = 1'bz;
                ctrl_brake_emergency    = 1'bz;
                ctrl_motor_accelerate   = 1'bz;
                ctrl_motor_maintain     = 1'bz;
            end

            default: begin
                ctrl_door               = 1'bz;
                ctrl_brake              = 1'bz;
                ctrl_brake_emergency    = 1'bz;
                ctrl_motor_accelerate   = 1'bz;
                ctrl_motor_maintain     = 1'bz;
            end
        endcase
    end
endmodule

ELEC 402/Assignment 1/fsm_tb.sv
`timescale 1s/1ms

module FSM_tb();
    //clock and reset
    logic   clk, rst;

    //inputs
    logic   depart_ready,
            door_obstruction,
            door_is_open,
            near_station, 
            at_station,
            track_obstruction;
    logic[7:0] cruise_speed, current_speed, crawl_speed;

    //outputs
    logic   ctrl_door,
            ctrl_brake,
            ctrl_brake_emergency,
            ctrl_motor_accelerate,
            ctrl_motor_maintain;

    //FSM Instantiation
    train_FSM DUT(
        clk, rst,

        depart_ready,
        door_obstruction,
        door_is_open,
        near_station, 
        at_station,
        track_obstruction,

        cruise_speed, current_speed, crawl_speed,

        ctrl_door,
        ctrl_brake,
        ctrl_brake_emergency,
        ctrl_motor_accelerate,
        ctrl_motor_maintain
    );


    always begin
        clk = 0; #1;
        clk = 1; #1;
    end


    initial begin
        //initial conditions, train is sitting at station with doors open
        {   rst,
            depart_ready,
            door_obstruction,
            current_speed,
            near_station, 
            track_obstruction} = 0;
        at_station = 1;
        door_is_open = 1;
        cruise_speed = 100; //cruise speed of 100 km/h
        crawl_speed = 5; //crawl speed to align with station when arriving
        #30;

        //signal to train it may close doors and leave station
        depart_ready = 1;

        //wait for door close signal
        while(1) begin
            if(ctrl_door == 0) break;
            else #1;
        end

        //doors closing
        #10; door_is_open = 0;

        //wait for FSM to enable motor acceleration
        while(1) begin
            if(ctrl_motor_accelerate) break;
            else #1;
        end

        at_station = 0;
        depart_ready = 0;

        //begin accelerating train. FSM will wait until current_speed = 100 km/h to switch to cruise state
        while(1) begin
            if(ctrl_motor_maintain) break;
            else begin
                current_speed = current_speed + 5;
                #2;
            end
        end

        //train will cruise until near_station signal is provided or unless something... unusual happens
        #30;

        //oh no something unusual happened!
        track_obstruction = 1;

        //wait until FSM outputs emergency brake signal, then begin slowing down current_speed
        while(1) begin
            if(ctrl_brake_emergency) break;
            else #1;
        end
        while(1) begin
            if(current_speed == 0) break;
            else current_speed = current_speed - 10;
            #2;
        end

        //after 10 seconds, obstruction is removed and train may continue
        #10;
        track_obstruction = 0;

        //wait for FSM to enable motor acceleration
        while(1) begin
            if(ctrl_motor_accelerate) break;
            else #1;
        end

        //begin accelerating train. FSM will wait until current_speed = 100 km/h to switch to cruise state
        while(1) begin
            if(ctrl_motor_maintain) break;
            else begin
                current_speed = current_speed + 5;
                #2;
            end
        end

        //train will cruise until near_station signal is provided or unless something... unusual happens
        #30;

        //nearing station
        near_station = 1;

        //wait until FSM outputs brake signal, then begin slowing down current_speed to crawl (5 km/h)
        while(1) begin
            if(ctrl_brake) break;
            else #1;
        end
        while(1) begin
            if(ctrl_motor_maintain) break;
            else current_speed = current_speed - 5;
            #2;
        end

        //train is now crawling, tell fsm when train aligned with platform
        #4;
        near_station = 0;
        at_station = 1;

        //wait for brake signal from fsm then stop train
        while(1) begin
            if(ctrl_brake) break;
            else #1;
        end
        current_speed = 0;

        //wait for door open signal from fsm
        while(1) begin
            if(ctrl_door == 1) break;
            else #1;
        end

        //doors closing
        #10; door_is_open = 1;

        #30;
        $stop;
    end
endmodule

ELEC 402/Assignment 1/vsim.vcd
$date
	Wed Sep 23 23:47:18 2020
$end
$version
	ModelSim Version 2020.1
$end
$timescale
	1ms
$end
$scope module FSM_tb $end
$var reg 1 ! clk $end
$var reg 1 " depart_ready $end
$var reg 1 # door_obstruction $end
$var reg 1 $ door_is_open $end
$var reg 8 % current_speed [7:0] $end
$var reg 8 & cruise_speed [7:0] $end
$var reg 1 ' near_station $end
$var reg 1 ( at_station $end
$var reg 1 ) track_obstruction $end
$var reg 1 * ctrl_door $end
$var reg 1 + ctrl_brake $end
$var reg 1 , ctrl_brake_emergency $end
$var reg 1 - ctrl_motor_accelerate $end
$var reg 1 . ctrl_motor_maintain $end
$var reg 1 / rst $end
$var reg 8 0 crawl_speed [7:0] $end
$scope module DUT $end
$var integer 32 1 state $end
$upscope $end
$upscope $end
$enddefinitions $end
#0
b0 !
b0 "
b0 #
b1 $
b0 %
b1100100 &
b0 '
b1 (
b0 )
b0 *
b0 +
b0 ,
b0 -
b0 .
b0 /
bx0x 1
b101 0
b0 !
b0 )
b0 '
b0 %
b0 #
b0 "
b0 /
b1 (
b1 $
b1100100 &
b101 0
b0 .
b0 -
b0 ,
b0 +
b0 *
#1000
b1 !
bx 1
b1 +
b1 *
#2000
b0 !
#3000
b1 !
#4000
b0 !
#5000
b1 !
#6000
b0 !
#7000
b1 !
#8000
b0 !
#9000
b1 !
#10000
b0 !
#11000
b1 !
#12000
b0 !
#13000
b1 !
#14000
b0 !
#15000
b1 !
#16000
b0 !
#17000
b1 !
#18000
b0 !
#19000
b1 !
#20000
b0 !
#21000
b1 !
#22000
b0 !
#23000
b1 !
#24000
b0 !
#25000
b1 !
#26000
b0 !
#27000
b1 !
#28000
b0 !
#29000
b1 !
#30000
b1 "
b0 !
#31000
b1 !
bx0xxxxx 1
b0 *
#32000
b0 !
#33000
b1 !
#34000
b0 !
#35000
b1 !
#36000
b0 !
#37000
b1 !
#38000
b0 !
#39000
b1 !
#40000
b0 !
#41000
b1 !
#42000
b0 $
b0 !
#43000
b1 !
bx0xxxx 1
#44000
b0 !
#45000
b1 !
bx0xxxxx 1
b1 -
b0 +
#46000
b0 (
b0 "
b101 %
b0 !
#47000
b1 !
#48000
b1010 %
b0 !
#49000
b1 !
#50000
b1111 %
b0 !
#51000
b1 !
#52000
b10100 %
b0 !
#53000
b1 !
#54000
b11001 %
b0 !
#55000
b1 !
#56000
b11110 %
b0 !
#57000
b1 !
#58000
b100011 %
b0 !
#59000
b1 !
#60000
b101000 %
b0 !
#61000
b1 !
#62000
b101101 %
b0 !
#63000
b1 !
#64000
b110010 %
b0 !
#65000
b1 !
#66000
b110111 %
b0 !
#67000
b1 !
#68000
b111100 %
b0 !
#69000
b1 !
#70000
b1000001 %
b0 !
#71000
b1 !
#72000
b1000110 %
b0 !
#73000
b1 !
#74000
b1001011 %
b0 !
#75000
b1 !
#76000
b1010000 %
b0 !
#77000
b1 !
#78000
b1010101 %
b0 !
#79000
b1 !
#80000
b1011010 %
b0 !
#81000
b1 !
#82000
b1011111 %
b0 !
#83000
b1 !
#84000
b1100100 %
b0 !
#85000
b1 !
bx 1
b1 .
b0 -
#86000
b0 !
#87000
b1 !
#88000
b0 !
#89000
b1 !
#90000
b0 !
#91000
b1 !
#92000
b0 !
#93000
b1 !
#94000
b0 !
#95000
b1 !
#96000
b0 !
#97000
b1 !
#98000
b0 !
#99000
b1 !
#100000
b0 !
#101000
b1 !
#102000
b0 !
#103000
b1 !
#104000
b0 !
#105000
b1 !
#106000
b0 !
#107000
b1 !
#108000
b0 !
#109000
b1 !
#110000
b0 !
#111000
b1 !
#112000
b0 !
#113000
b1 !
#114000
b0 !
#115000
b1 !
#116000
b1 )
b0 !
#117000
b1 !
bx 1
b0 .
b1 ,
#118000
b1011010 %
b0 !
#119000
b1 !
#120000
b1010000 %
b0 !
#121000
b1 !
#122000
b1000110 %
b0 !
#123000
b1 !
#124000
b111100 %
b0 !
#125000
b1 !
#126000
b110010 %
b0 !
#127000
b1 !
#128000
b101000 %
b0 !
#129000
b1 !
#130000
b11110 %
b0 !
#131000
b1 !
#132000
b10100 %
b0 !
#133000
b1 !
#134000
b1010 %
b0 !
#135000
b1 !
#136000
b0 %
b0 !
#137000
b1 !
#138000
b0 !
#139000
b1 !
#140000
b0 !
#141000
b1 !
#142000
b0 !
#143000
b1 !
#144000
b0 !
#145000
b1 !
#146000
b0 !
#147000
b1 !
#148000
b0 )
b0 !
#149000
b1 !
bx0xxxxx 1
b1 -
b0 ,
#150000
b101 %
b0 !
#151000
b1 !
#152000
b1010 %
b0 !
#153000
b1 !
#154000
b1111 %
b0 !
#155000
b1 !
#156000
b10100 %
b0 !
#157000
b1 !
#158000
b11001 %
b0 !
#159000
b1 !
#160000
b11110 %
b0 !
#161000
b1 !
#162000
b100011 %
b0 !
#163000
b1 !
#164000
b101000 %
b0 !
#165000
b1 !
#166000
b101101 %
b0 !
#167000
b1 !
#168000
b110010 %
b0 !
#169000
b1 !
#170000
b110111 %
b0 !
#171000
b1 !
#172000
b111100 %
b0 !
#173000
b1 !
#174000
b1000001 %
b0 !
#175000
b1 !
#176000
b1000110 %
b0 !
#177000
b1 !
#178000
b1001011 %
b0 !
#179000
b1 !
#180000
b1010000 %
b0 !
#181000
b1 !
#182000
b1010101 %
b0 !
#183000
b1 !
#184000
b1011010 %
b0 !
#185000
b1 !
#186000
b1011111 %
b0 !
#187000
b1 !
#188000
b1100100 %
b0 !
#189000
b1 !
bx 1
b1 .
b0 -
#190000
b0 !
#191000
b1 !
#192000
b0 !
#193000
b1 !
#194000
b0 !
#195000
b1 !
#196000
b0 !
#197000
b1 !
#198000
b0 !
#199000
b1 !
#200000
b0 !
#201000
b1 !
#202000
b0 !
#203000
b1 !
#204000
b0 !
#205000
b1 !
#206000
b0 !
#207000
b1 !
#208000
b0 !
#209000
b1 !
#210000
b0 !
#211000
b1 !
#212000
b0 !
#213000
b1 !
#214000
b0 !
#215000
b1 !
#216000
b0 !
#217000
b1 !
#218000
b0 !
#219000
b1 !
#220000
b1 '
b0 !
#221000
b1 !
bx 1
b0 .
b1 +
#222000
b1011111 %
b0 !
#223000
b1 !
#224000
b1011010 %
b0 !
#225000
b1 !
#226000
b1010101 %
b0 !
#227000
b1 !
#228000
b1010000 %
b0 !
#229000
b1 !
#230000
b1001011 %
b0 !
#231000
b1 !
#232000
b1000110 %
b0 !
#233000
b1 !
#234000
b1000001 %
b0 !
#235000
b1 !
#236000
b111100 %
b0 !
#237000
b1 !
#238000
b110111 %
b0 !
#239000
b1 !
#240000
b110010 %
b0 !
#241000
b1 !
#242000
b101101 %
b0 !
#243000
b1 !
#244000
b101000 %
b0 !
#245000
b1 !
#246000
b100011 %
b0 !
#247000
b1 !
#248000
b11110 %
b0 !
#249000
b1 !
#250000
b11001 %
b0 !
#251000
b1 !
#252000
b10100 %
b0 !
#253000
b1 !
#254000
b1111 %
b0 !
#255000
b1 !
#256000
b1010 %
b0 !
#257000
b1 !
#258000
b101 %
b0 !
#259000
b1 !
bx0 1
b1 .
b0 +
#260000
b0 !
#261000
b1 !
#262000
b0 !
#263000
b1 !
#264000
b0 '
b1 (
b0 !
#265000
b1 !
bx 1
b0 .
b1 +
#266000
b0 %
b0 !
#267000
b1 !
bx 1
b1 *
#268000
b0 !
#269000
b1 !
#270000
b0 !
#271000
b1 !
#272000
b0 !
#273000
b1 !
#274000
b0 !
#275000
b1 !
#276000
b0 !
#277000
b1 !
#278000
b1 $
b0 !
#279000
b1 !
bx 1
#280000
b0 !
#281000
b1 !
#282000
b0 !
#283000
b1 !
#284000
b0 !
#285000
b1 !
#286000
b0 !
#287000
b1 !
#288000
b0 !
#289000
b1 !
#290000
b0 !
#291000
b1 !
#292000
b0 !
#293000
b1 !
#294000
b0 !
#295000
b1 !
#296000
b0 !
#297000
b1 !
#298000
b0 !
#299000
b1 !
#300000
b0 !
#301000
b1 !
#302000
b0 !
#303000
b1 !
#304000
b0 !
#305000
b1 !
#306000
b0 !
#307000
b1 !
